struct_eqtable/__init__.py
struct_eqtable/version.py
struct_eqtable/internvl/__init__.py
struct_eqtable/internvl/conversation.py
struct_eqtable/internvl/internvl.py
struct_eqtable/internvl/internvl_lmdeploy.py
struct_eqtable/pix2s/__init__.py
struct_eqtable/pix2s/pix2s.py
struct_eqtable/pix2s/pix2s_trt.py
struct_eqtable-0.3.3.dist-info/LICENSE
struct_eqtable-0.3.3.dist-info/METADATA
struct_eqtable-0.3.3.dist-info/WHEEL
struct_eqtable-0.3.3.dist-info/top_level.txt
struct_eqtable-0.3.3.dist-info/RECORD
