Metadata-Version: 2.1
Name: struct-eqtable
Version: 0.3.3
Summary: A High-efficiency Open-source Toolkit for Table-to-Latex Transformation
Home-page: https://github.com/UniModal4Reasoning/StructEqTable-Deploy
Author: Hongbin Zhou, Xiangchao Yan, Bo Zhang
Author-email: zhangbo@pjlab.org.cn
License: Apache License 2.0
Requires-Python: >=3.9
License-File: LICENSE
Requires-Dist: torch
Requires-Dist: transformers <=4.45.2
